daltonlens/__init__.py
daltonlens/__main__.py
daltonlens/convert.py
daltonlens/generate.py
daltonlens/geometry.py
daltonlens/main.py
daltonlens/simulate.py
daltonlens/utils.py
daltonlens/data/mask_1.png
daltonlens/data/mask_2.png
daltonlens/data/mask_3.png
daltonlens/data/mask_5.png
daltonlens/data/mask_6.png
daltonlens/data/mask_7.png
daltonlens/data/mask_8.png
daltonlens/data/mask_9.png
daltonlens-0.1.5.dist-info/LICENSE
daltonlens-0.1.5.dist-info/METADATA
daltonlens-0.1.5.dist-info/WHEEL
daltonlens-0.1.5.dist-info/entry_points.txt
daltonlens-0.1.5.dist-info/top_level.txt
daltonlens-0.1.5.dist-info/RECORD
