Metadata-Version: 2.1
Name: daltonlens
Version: 0.1.5
Summary: Utility to help colorblind people by providing color filters and highlighting tools.
Home-page: https://github.com/DaltonLens/DaltonLens-Python
Author: Nicolas Burrus
Author-email: nicolas@burrus.name
License: UNKNOWN
Project-URL: Bug Tracker, https://github.com/DaltonLens/DaltonLens-Python/issues
Platform: UNKNOWN
Classifier: Programming Language :: Python :: 3
Classifier: License :: OSI Approved :: MIT License
Classifier: Operating System :: OS Independent
Requires-Python: >=3.7
License-File: LICENSE
Requires-Dist: numpy
Requires-Dist: Pillow
